SOC-32bit-project/RTL_code/RTL_code_1/RTL_sim/sys/rtl/sys.v
// Generator : SpinalHDL v1.8.1    git head : 2a7592004363e5b40ec43e1f122ed8641cd8965b
// Component : sys
// Git hash  : 1540a3423eb7ba89e1e6132ee61a59d588311a17

`timescale 1ns/1ps

module sys (
  input               io_ckl,
  input               io_rst_n,
  output              io_sys_clk,
  output              io_sys_rst_n,
  input               clk,
  input               reset
);

  reg                 clkarea_rst_one;

  assign io_sys_clk = io_ckl;
  assign io_sys_rst_n = clkarea_rst_one;
  always @(posedge io_ckl) begin
    if(!io_rst_n) begin
      clkarea_rst_one <= 1'b0;
    end else begin
      clkarea_rst_one <= 1'b1;
    end
  end


endmodule

SOC-32bit-project/RTL_code/RTL_code_1/RTL_sim/sys/test.vcd
$version Generated by VerilatedVcd $end
$timescale 1ps $end

 $scope module TOP $end
  $var wire  1 ' clk $end
  $var wire  1 # io_ckl $end
  $var wire  1 $ io_rst_n $end
  $var wire  1 % io_sys_clk $end
  $var wire  1 & io_sys_rst_n $end
  $var wire  1 ( reset $end
  $scope module sys $end
   $var wire  1 ' clk $end
   $var wire  1 ) clkarea_rst_one $end
   $var wire  1 # io_ckl $end
   $var wire  1 $ io_rst_n $end
   $var wire  1 % io_sys_clk $end
   $var wire  1 & io_sys_rst_n $end
   $var wire  1 ( reset $end
  $upscope $end
 $upscope $end
$enddefinitions $end


#0
0#
1$
0%
0&
1'
0(
0)
#5
1#
1%
1&
1)
#10
0#
0%
#15
1#
1%
#20
0#
0%
#25
1#
1%
#30
0#
0%
#35
1#
1%
#40
0#
0%
#45
1#
1%
#50
0#
0%
#55
1#
1%
#60
0#
0%
#65
1#
1%
#70
0#
0%
#75
1#
1%
#80
0#
0%
#85
1#
1%
#90
0#
0%
#95
1#
1%
